{
  "book": "Salamo",
  "chapter": 128,
  "verses": {
    "1": "[Hira misy hevitra ambaratonga.] SAMBATRA izay rehetra matahotra an' i Jehovah! dia izay mandeha amin' ny lalany.",
    "2": "Fa hohaninao tokoa ny asan' ny tananao; sambatra sady ambinina ianao.",
    "3": "Ny vadinao dia ho tahaka ny voaloboka mahavokatra ao anatin' ny tranonao; ny zanakao dia ho tahaka ny zanak' oliva manodidina ny latabatrao.",
    "4": "Indro, fa toy izany no hitahiana izay lehilahy matahotra an' i Jehovah.",
    "5": "Hitahy anao avy ao Ziona anie Jehovah; ary hahita ny fahasoavan' i Jerosalema amin' ny andro rehetra hiainanao ianao.",
    "6": "Eny, hahita ny zafinao anie ianao; fiadanana anie ho amin' ny Isiraely."
  }
}