{
  "chapter": 21,
  "verses": [
    {
      "v": 1,
      "text": "Dia namaly Joba ka nanao hoe:"
    },
    {
      "v": 2,
      "text": "Mihainoa dia mihainoa ny teniko, ary aoka izany no ho fampiononanareo ahy."
    },
    {
      "v": 3,
      "text": "\"Mandefera amiko fa mba hiteny aho; ary rehefa tapitra ny teniko, dia mandatsalatsà.\""
    },
    {
      "v": 4,
      "text": "Raha ny amiko, moa ny olona no itarainako? raha izany, nahoana no tsy hitebiteby ny fanahiko?"
    },
    {
      "v": 5,
      "text": "Jereo aho dia aoka ho talanjona ianareo, ary atampeno ny vavanareo ny tananareo."
    },
    {
      "v": 6,
      "text": "Eny, raha mahatsiaro izany aho, dia raiki-tahotra, sady toran-kovitra ny tenako:"
    },
    {
      "v": 7,
      "text": "Nahoana no velona ny ratsy fanahy ka sady tratrantitra no be hery?"
    },
    {
      "v": 8,
      "text": "Ny zanany mitoetra tsara eo anatrehany, ary ny taranany eo anoloan' ny masony."
    },
    {
      "v": 9,
      "text": "Ny ankohonany miadana ka tsy manan-tahotra, ary ny tsorakazon' Andriamanitra tsy mamely azy."
    },
    {
      "v": 10,
      "text": "\"Ny ombilahiny mampiteraka ka mahavanona; ny ombivaviny miteraka ka tsy mamotsotra.\""
    },
    {
      "v": 11,
      "text": "Mamoaka ny zanany madinika toy ny ondry aman' osy izy, ka mandihy ny zanany."
    },
    {
      "v": 12,
      "text": "Mihoby mitondra ny ampongatapaka sy ny harpa izy, ary mifaly amin' ny feon' ny orga."
    },
    {
      "v": 13,
      "text": "Mandany ny androny amin' ny harena izy, ary amin' ny indray mipi-maso dia lasa any am-pasana."
    },
    {
      "v": 14,
      "text": "Noho izany no itenenany amin' Andriamanitra hoe: Mialà aminay, fa tsy mba irinay ny hahalala ny lalanao."
    },
    {
      "v": 15,
      "text": "Zinona izay Tsitoha, no hotompoinay? ary inona no soa ho azonay, raha mivavaka aminy?"
    },
    {
      "v": 16,
      "text": "Indro, ny fananany tsy eo an-tanany: lavitra ahy ny fisainan' ny ratsy fanahy."
    },
    {
      "v": 17,
      "text": "Indraindray foana no mba maty ny jiron' ny ratsy fanahy, sy tonga ny loza manjo azy! Mizara fahoriana Andriamanitra noho ny fahatezerany."
    },
    {
      "v": 18,
      "text": "Tahaka ny mololo voatetika indaosin' ny rivotra izy sy tahaka ny akofa entin' ny tafio-drivotra."
    },
    {
      "v": 19,
      "text": "\"Angonin' Andriamanitra eo amin' ny zanany ny helo-drainy; hovaliany izy ka ho fantany izany.\""
    },
    {
      "v": 20,
      "text": "Ny masony hahita ny fandringanana ny tenany, ary hisotro amin' ny fahatezeran' ny Tsitoha izy."
    },
    {
      "v": 21,
      "text": "Fa inona moa no mahafaly azy ny amin' ny taranany mandimby azy raha tapaka antenantenany ny isan' ny volana iainany?"
    },
    {
      "v": 22,
      "text": "Moa Andriamanitra va no hampianarim-pahalalana? nefa Izy no mitsara ireo izay ambony."
    },
    {
      "v": 23,
      "text": "Maty ny anankiray ao amin' ny fahafenoan' ny heriny, izay sady miadana tokoa no tsy manana ahiahy."
    },
    {
      "v": 24,
      "text": "Feno ronono ny tratrany, ary vonton-tsoka ny taolany."
    },
    {
      "v": 25,
      "text": "Ary ny anankiray maty amin' ny fahorian' ny fanahiny kosa ka tsy mba nanandrana soa akory."
    },
    {
      "v": 26,
      "text": "Samy handry ao amin' ny vovoka izy roa tonta ka ho rakotry ny kankana ny tenany."
    },
    {
      "v": 27,
      "text": "\"Indro, fantatro ny hevitrareo sy ny saim-petsy amelezanareo ahy;\""
    },
    {
      "v": 28,
      "text": "Fa hoy ianareo: Aiza ny tranon' ny zanak' andriana? ary aiza ny lay fitoeran' ny ratsy fanahy?"
    },
    {
      "v": 29,
      "text": "Tsy nanontanianareo va izay mpandeha an-tany lavitra? ary tsy fantatrareo va ny famantaran' izy ireny?"
    },
    {
      "v": 30,
      "text": "Fa ny ratsy fanahy dia voatahiry ho amin' ny andro fandringanana? Hoentina amin' ny andro fahatezerana izy."
    },
    {
      "v": 31,
      "text": "Iza no hanambara ny lalany eo anatrehany? ary iza no hamaly azy ny amin' izay zavatra nataony?"
    },
    {
      "v": 32,
      "text": "Hoentina any an-tany fandevenana izy, ary hitoetra any am-pasana."
    },
    {
      "v": 33,
      "text": "Ho mamy aminy ny bainga any an-dohasaha, ary ny olona rehetra hanaraka azy toy ny nandehanan' ny maro tany alohany."
    },
    {
      "v": 34,
      "text": "Endrey, mba mampionona ahy foana ianareo, nefa hita fa misy fitaka ao amin' ny famalianareo!"
    }
  ]
}